{
  "results": [
    {
      "mse": 0.0,
      "n": 10000,
      "name": "oracle",
      "static_arbitrage": {
        "M": 12,
        "curve": {
          "app_err": [
            0.0,
            0.0,
            0.0,
            0.0,
            0.0,
            0.0,
            0.0,
            0.0,
            0.0,
            0.0,
            0.0,
            0.0,
            0.0,
            0.0,
            0.0,
            0.0,
            0.0,
            0.0,
            0.0,
            0.0,
            0.0,
            0.0,
            0.0,
            0.0,
            0.0,
            0.0,
            0.0,
            0.0,
            0.0,
            0.0,
            0.0,
            0.0,
            0.0,
            0.0,
            0.0,
            0.0,
            0.0,
            0.0,
            0.0,
            0.0,
            0.0,
            0.0,
            0.0,
            0.0,
            0.0,
            0.0,
            0.0,
            0.0,
            0.0,
            0.0
          ],
          "t": [
            200,
            400,
            600,
            800,
            1000,
            1200,
            1400,
            1600,
            1800,
            2000,
            2200,
            2400,
            2600,
            2800,
            3000,
            3200,
            3400,
            3600,
            3800,
            4000,
            4200,
            4400,
            4600,
            4800,
            5000,
            5200,
            5400,
            5600,
            5800,
            6000,
            6200,
            6400,
            6600,
            6800,
            7000,
            7200,
            7400,
            7600,
            7800,
            8000,
            8200,
            8400,
            8600,
            8800,
            9000,
            9200,
            9400,
            9600,
            9800,
            10000
          ]
        },
        "curve_every": 200,
        "final_app_err": 0.0,
        "frac_any_violated": 0.0,
        "include_box": true,
        "mean_pos": 0.0,
        "structure": "equal"
      }
    },
    {
      "mse": 0.020894151113207273,
      "n": 10000,
      "name": "noisy(sigma=0.15)",
      "static_arbitrage": {
        "M": 12,
        "curve": {
          "app_err": [
            0.08732782467730964,
            0.0845154794647623,
            0.08701206427159054,
            0.08541054537353211,
            0.08194676621925533,
            0.0822560465358466,
            0.08178364751709016,
            0.08229391574262626,
            0.08402383332988772,
            0.08435971906046624,
            0.0846603585997076,
            0.08589380450400105,
            0.08558646508824426,
            0.08552347712943248,
            0.08493852092838207,
            0.08455546059020745,
            0.08393150608352323,
            0.08320278822874222,
            0.0831641526306037,
            0.08359737247222093,
            0.08390552566002839,
            0.08346918840148969,
            0.08388010818332196,
            0.08366114273456114,
            0.08387390180439991,
            0.08373783195929856,
            0.08301933621569324,
            0.08287154367298348,
            0.08273934506301746,
            0.08273655555719446,
            0.08252619941571344,
            0.08272815969414352,
            0.08220696465063432,
            0.08190669895493198,
            0.08245782612061084,
            0.08225567998344539,
            0.08231792773595918,
            0.0822579096548169,
            0.08224408018364565,
            0.08202931959118863,
            0.08224665073558668,
            0.08246973738075337,
            0.08244822505663169,
            0.08234794268666434,
            0.0822926519835259,
            0.08236020180693523,
            0.08243637800406664,
            0.08246402414675844,
            0.08239376702433705,
            0.08273182523138314
          ],
          "t": [
            200,
            400,
            600,
            800,
            1000,
            1200,
            1400,
            1600,
            1800,
            2000,
            2200,
            2400,
            2600,
            2800,
            3000,
            3200,
            3400,
            3600,
            3800,
            4000,
            4200,
            4400,
            4600,
            4800,
            5000,
            5200,
            5400,
            5600,
            5800,
            6000,
            6200,
            6400,
            6600,
            6800,
            7000,
            7200,
            7400,
            7600,
            7800,
            8000,
            8200,
            8400,
            8600,
            8800,
            9000,
            9200,
            9400,
            9600,
            9800,
            10000
          ]
        },
        "curve_every": 200,
        "final_app_err": 0.08273182523138314,
        "frac_any_violated": 0.9987,
        "include_box": true,
        "mean_pos": 0.04069950524875321,
        "structure": "equal"
      }
    },
    {
      "mse": 0.01264820656530022,
      "n": 10000,
      "name": "bundle_diff(sample_steps=4,mc=16,median)",
      "static_arbitrage": {
        "M": 12,
        "curve": {
          "app_err": [
            0.00023213155567646025,
            0.00024085670709609987,
            0.00025452089806397756,
            0.0002530275657773018,
            0.0002548810541629791,
            0.0002540626190602779,
            0.0002529059776238033,
            0.0002524059126153588,
            0.0002528146116269959,
            0.00025280824303627013,
            0.0002522220868955959,
            0.000252442363028725,
            0.0002521477954892012,
            0.00025352142485124727,
            0.000253450907766819,
            0.00025352404685691,
            0.0002529524639248848,
            0.00025238987679282823,
            0.00025130598168624077,
            0.00025055796653032306,
            0.000250613425104391,
            0.00025016945871439845,
            0.0002496710030928902,
            0.0002494230788821975,
            0.0002491379052400589,
            0.00024864863174465986,
            0.0002490664687421587,
            0.0002498457447758743,
            0.00025008478426727756,
            0.0002498942278325558,
            0.00024927545819551715,
            0.00024923528428189457,
            0.0002492940866134383,
            0.0002494358567192274,
            0.0002497482459459986,
            0.000249580145917005,
            0.00024999446361451534,
            0.00025027634281861157,
            0.00025030135344236324,
            0.00025038750469684603,
            0.0002506258275087287,
            0.00025074673018285205,
            0.0002511291344498479,
            0.00025112262165004557,
            0.0002512171442310015,
            0.0002518419038666331,
            0.00025162546796367525,
            0.000251418388603876,
            0.0002516580912835744,
            0.00025131003335118296
          ],
          "t": [
            200,
            400,
            600,
            800,
            1000,
            1200,
            1400,
            1600,
            1800,
            2000,
            2200,
            2400,
            2600,
            2800,
            3000,
            3200,
            3400,
            3600,
            3800,
            4000,
            4200,
            4400,
            4600,
            4800,
            5000,
            5200,
            5400,
            5600,
            5800,
            6000,
            6200,
            6400,
            6600,
            6800,
            7000,
            7200,
            7400,
            7600,
            7800,
            8000,
            8200,
            8400,
            8600,
            8800,
            9000,
            9200,
            9400,
            9600,
            9800,
            10000
          ]
        },
        "curve_every": 200,
        "final_app_err": 0.00025131003335118296,
        "frac_any_violated": 1.0,
        "include_box": true,
        "mean_pos": 5.000934340059757e-05,
        "structure": "equal"
      }
    },
    {
      "mse": 0.012414783732957527,
      "n": 10000,
      "name": "bundle_diff(sample_steps=8,mc=16,median)",
      "static_arbitrage": {
        "M": 12,
        "curve": {
          "app_err": [
            0.0002314227819442749,
            0.00023281827569007874,
            0.00023780922094980876,
            0.000238864216953516,
            0.00024057799577713012,
            0.0002403843030333519,
            0.00024059716079916272,
            0.00024034622125327588,
            0.00023965608742502,
            0.00024026088044047355,
            0.00024009065533226186,
            0.00024055154373248418,
            0.0002406721906020091,
            0.0002413914991276605,
            0.00024133177598317465,
            0.00024098333436995746,
            0.00024061884073650137,
            0.00024031536239716743,
            0.00023999646894241634,
            0.0002399526033550501,
            0.00023989720003945487,
            0.00023935385725714945,
            0.00023928334855515023,
            0.00023861582390964032,
            0.00023821860402822495,
            0.00023792364849494055,
            0.0002377230191120395,
            0.00023778376302548818,
            0.0002377904116593558,
            0.00023756608987847964,
            0.00023733547498141567,
            0.00023733495851047337,
            0.00023733757323387897,
            0.00023738309850587563,
            0.00023748851141759328,
            0.00023745887291928133,
            0.00023738770770865517,
            0.00023775160116584678,
            0.0002380691239467034,
            0.00023831862211227416,
            0.00023832804727845077,
            0.0002383147455042317,
            0.0002384029857294504,
            0.00023845285431227901,
            0.0002385927215218544,
            0.00023870037544680678,
            0.00023866025453552286,
            0.00023872084993248183,
            0.00023879394391361548,
            0.0002386116549372673
          ],
          "t": [
            200,
            400,
            600,
            800,
            1000,
            1200,
            1400,
            1600,
            1800,
            2000,
            2200,
            2400,
            2600,
            2800,
            3000,
            3200,
            3400,
            3600,
            3800,
            4000,
            4200,
            4400,
            4600,
            4800,
            5000,
            5200,
            5400,
            5600,
            5800,
            6000,
            6200,
            6400,
            6600,
            6800,
            7000,
            7200,
            7400,
            7600,
            7800,
            8000,
            8200,
            8400,
            8600,
            8800,
            9000,
            9200,
            9400,
            9600,
            9800,
            10000
          ]
        },
        "curve_every": 200,
        "final_app_err": 0.0002386116549372673,
        "frac_any_violated": 1.0,
        "include_box": true,
        "mean_pos": 4.4229652732610705e-05,
        "structure": "equal"
      }
    },
    {
      "mse": 0.012540323960472164,
      "n": 10000,
      "name": "bundle_diff(sample_steps=16,mc=16,median)",
      "static_arbitrage": {
        "M": 12,
        "curve": {
          "app_err": [
            0.00023389436304569245,
            0.0002320200763642788,
            0.00023521752407153448,
            0.00023622165434062482,
            0.00023772469907999038,
            0.0002396293170750141,
            0.00023923545543636594,
            0.00023998447693884372,
            0.0002401857285035981,
            0.00024077976495027542,
            0.00024058087982914664,
            0.00024126123016079268,
            0.0002418863486785155,
            0.00024248031367148673,
            0.00024289254595836004,
            0.00024223247775807976,
            0.00024202556513688143,
            0.00024166328004664845,
            0.00024164160027315742,
            0.00024162008799612523,
            0.00024188516927616937,
            0.00024141500449993393,
            0.0002414998298753863,
            0.00024050826362023752,
            0.00024041444212198257,
            0.0002403377569638766,
            0.00024063800910004862,
            0.00024045071032430444,
            0.00024045532761976637,
            0.00024022057776649792,
            0.0002398955401393675,
            0.00024013247690163553,
            0.00024015155818426248,
            0.0002402274847468909,
            0.00024019377785069603,
            0.00024017483823829226,
            0.00023992890542423403,
            0.00024046167241115318,
            0.00024063247232100903,
            0.00024074868019670248,
            0.00024073621939595151,
            0.00024061525684027446,
            0.00024088679184747298,
            0.00024109505116939544,
            0.0002413320889075597,
            0.00024152929935118426,
            0.00024152363947731385,
            0.00024136656352008383,
            0.00024144345628363746,
            0.00024127949699759483
          ],
          "t": [
            200,
            400,
            600,
            800,
            1000,
            1200,
            1400,
            1600,
            1800,
            2000,
            2200,
            2400,
            2600,
            2800,
            3000,
            3200,
            3400,
            3600,
            3800,
            4000,
            4200,
            4400,
            4600,
            4800,
            5000,
            5200,
            5400,
            5600,
            5800,
            6000,
            6200,
            6400,
            6600,
            6800,
            7000,
            7200,
            7400,
            7600,
            7800,
            8000,
            8200,
            8400,
            8600,
            8800,
            9000,
            9200,
            9400,
            9600,
            9800,
            10000
          ]
        },
        "curve_every": 200,
        "final_app_err": 0.00024127949699759483,
        "frac_any_violated": 1.0,
        "include_box": true,
        "mean_pos": 4.488955618192752e-05,
        "structure": "equal"
      }
    },
    {
      "mse": 0.012610419068106683,
      "n": 10000,
      "name": "bundle_diff(sample_steps=32,mc=16,median)",
      "static_arbitrage": {
        "M": 12,
        "curve": {
          "app_err": [
            0.00023362420499324797,
            0.00023231903091073037,
            0.000234778660039107,
            0.00023599189706146717,
            0.00023820262402296066,
            0.00024040298536419868,
            0.0002400027428354536,
            0.00024094920605421065,
            0.00024151270588239034,
            0.0002418838068842888,
            0.0002416490763425827,
            0.00024224197181562583,
            0.00024293621572164388,
            0.0002435356830911977,
            0.00024394181619087854,
            0.00024345509940758346,
            0.00024318813620244754,
            0.00024280135209361713,
            0.00024282309765878476,
            0.00024265567399561405,
            0.000242966961647783,
            0.0002425131117078391,
            0.00024253988233597382,
            0.00024154648339996736,
            0.0002415604129433632,
            0.0002414565648023899,
            0.00024178677824912247,
            0.00024159028194844722,
            0.00024160959725749904,
            0.0002414136491715908,
            0.00024101067334413528,
            0.00024128330522216857,
            0.00024127051347132885,
            0.00024138944442657863,
            0.0002412879541516304,
            0.0002412361641310983,
            0.00024091182528315365,
            0.00024143380358030922,
            0.00024157600716138498,
            0.00024166849628090857,
            0.00024167440559079008,
            0.00024155674857043085,
            0.00024185540977605553,
            0.00024209479801356792,
            0.00024238014469544093,
            0.00024261001092584238,
            0.00024256060335864412,
            0.00024240600178018212,
            0.00024246857786665158,
            0.00024227616861462593
          ],
          "t": [
            200,
            400,
            600,
            800,
            1000,
            1200,
            1400,
            1600,
            1800,
            2000,
            2200,
            2400,
            2600,
            2800,
            3000,
            3200,
            3400,
            3600,
            3800,
            4000,
            4200,
            4400,
            4600,
            4800,
            5000,
            5200,
            5400,
            5600,
            5800,
            6000,
            6200,
            6400,
            6600,
            6800,
            7000,
            7200,
            7400,
            7600,
            7800,
            8000,
            8200,
            8400,
            8600,
            8800,
            9000,
            9200,
            9400,
            9600,
            9800,
            10000
          ]
        },
        "curve_every": 200,
        "final_app_err": 0.00024227616861462593,
        "frac_any_violated": 1.0,
        "include_box": true,
        "mean_pos": 4.5326703476409116e-05,
        "structure": "equal"
      }
    },
    {
      "mse": 0.012648622157442616,
      "n": 10000,
      "name": "bundle_diff(sample_steps=64,mc=16,median)",
      "static_arbitrage": {
        "M": 12,
        "curve": {
          "app_err": [
            0.0002342207729816437,
            0.00023209230974316597,
            0.000234458160897096,
            0.00023605759255588055,
            0.00023834642022848128,
            0.0002404840166370074,
            0.00024021219462156296,
            0.0002411208162084222,
            0.0002414429063598315,
            0.00024193649366497993,
            0.00024175726215947758,
            0.00024220211431384087,
            0.00024289499681729536,
            0.000243525787123612,
            0.00024405516187349954,
            0.00024368938058614732,
            0.00024345718324184418,
            0.00024310901761054993,
            0.00024315540531748219,
            0.00024300248734652997,
            0.00024333524029879344,
            0.00024288414046168326,
            0.00024286606227574142,
            0.0002417704990754525,
            0.00024169524759054184,
            0.00024158372758672787,
            0.000241891344388326,
            0.00024170555706535068,
            0.00024176112536726326,
            0.00024152589092652003,
            0.00024110399186611176,
            0.00024140596156939863,
            0.0002413729363770196,
            0.0002414924793821924,
            0.00024137517596994128,
            0.00024134361288613744,
            0.00024102240096072892,
            0.00024144076497146957,
            0.0002416048743403875,
            0.00024168374110013246,
            0.00024169200168150227,
            0.000241610123110669,
            0.00024189915508031844,
            0.00024215138517320157,
            0.00024240502963463465,
            0.00024262451809709486,
            0.00024258348258568885,
            0.00024247331894002854,
            0.00024257441754547916,
            0.00024239910431206226
          ],
          "t": [
            200,
            400,
            600,
            800,
            1000,
            1200,
            1400,
            1600,
            1800,
            2000,
            2200,
            2400,
            2600,
            2800,
            3000,
            3200,
            3400,
            3600,
            3800,
            4000,
            4200,
            4400,
            4600,
            4800,
            5000,
            5200,
            5400,
            5600,
            5800,
            6000,
            6200,
            6400,
            6600,
            6800,
            7000,
            7200,
            7400,
            7600,
            7800,
            8000,
            8200,
            8400,
            8600,
            8800,
            9000,
            9200,
            9400,
            9600,
            9800,
            10000
          ]
        },
        "curve_every": 200,
        "final_app_err": 0.00024239910431206226,
        "frac_any_violated": 1.0,
        "include_box": true,
        "mean_pos": 4.507504620899757e-05,
        "structure": "equal"
      }
    }
  ],
  "train_meta": {
    "final_loss": 0.10612816575914621,
    "steps": 4000
  }
}
