{
  "results": [
    {
      "mse": 0.0,
      "n": 10000,
      "name": "oracle",
      "static_arbitrage": {
        "M": 10,
        "curve": {
          "app_err": [
            0.0,
            0.0,
            0.0,
            0.0,
            0.0,
            0.0,
            0.0,
            0.0,
            0.0,
            0.0,
            0.0,
            0.0,
            0.0,
            0.0,
            0.0,
            0.0,
            0.0,
            0.0,
            0.0,
            0.0,
            0.0,
            0.0,
            0.0,
            0.0,
            0.0,
            0.0,
            0.0,
            0.0,
            0.0,
            0.0,
            0.0,
            0.0,
            0.0,
            0.0,
            0.0,
            0.0,
            0.0,
            0.0,
            0.0,
            0.0,
            0.0,
            0.0,
            0.0,
            0.0,
            0.0,
            0.0,
            0.0,
            0.0,
            0.0,
            0.0
          ],
          "t": [
            200,
            400,
            600,
            800,
            1000,
            1200,
            1400,
            1600,
            1800,
            2000,
            2200,
            2400,
            2600,
            2800,
            3000,
            3200,
            3400,
            3600,
            3800,
            4000,
            4200,
            4400,
            4600,
            4800,
            5000,
            5200,
            5400,
            5600,
            5800,
            6000,
            6200,
            6400,
            6600,
            6800,
            7000,
            7200,
            7400,
            7600,
            7800,
            8000,
            8200,
            8400,
            8600,
            8800,
            9000,
            9200,
            9400,
            9600,
            9800,
            10000
          ]
        },
        "curve_every": 200,
        "final_app_err": 0.0,
        "frac_any_violated": 0.0,
        "include_box": true,
        "mean_pos": 0.0,
        "structure": "frechet"
      }
    },
    {
      "mse": 0.019850838823906244,
      "n": 10000,
      "name": "noisy(sigma=0.15)",
      "static_arbitrage": {
        "M": 10,
        "curve": {
          "app_err": [
            0.03554783964409552,
            0.032593035671261913,
            0.03046046355158852,
            0.028875242304666062,
            0.02953109430765558,
            0.030656607238490667,
            0.031015259880852405,
            0.031114814422651266,
            0.031296256620516695,
            0.031375099042090446,
            0.03173357841006115,
            0.032271518367066744,
            0.03170816392847788,
            0.03156712137660824,
            0.0318083782896185,
            0.03206190282917494,
            0.031672385719467046,
            0.03153328918360771,
            0.031042947559503018,
            0.030445599931265097,
            0.030638281529934457,
            0.03025638636411515,
            0.03015056067966939,
            0.030136321395483865,
            0.030065356866567788,
            0.03017906216493135,
            0.030621202297057476,
            0.0303506295028559,
            0.030102502678908884,
            0.03007093129201691,
            0.030564520222913952,
            0.030500552158019882,
            0.030841268617642654,
            0.03064936528340138,
            0.030598315448233143,
            0.03046184396878739,
            0.03031781772486172,
            0.030205340713483863,
            0.03030198483471783,
            0.030528642466966648,
            0.03049856258860627,
            0.03047427184799692,
            0.030544462720665647,
            0.030381774527031266,
            0.030505785034566777,
            0.03040822510380212,
            0.03039839088795217,
            0.030775313439899213,
            0.03111324702190069,
            0.0312558983831845
          ],
          "t": [
            200,
            400,
            600,
            800,
            1000,
            1200,
            1400,
            1600,
            1800,
            2000,
            2200,
            2400,
            2600,
            2800,
            3000,
            3200,
            3400,
            3600,
            3800,
            4000,
            4200,
            4400,
            4600,
            4800,
            5000,
            5200,
            5400,
            5600,
            5800,
            6000,
            6200,
            6400,
            6600,
            6800,
            7000,
            7200,
            7400,
            7600,
            7800,
            8000,
            8200,
            8400,
            8600,
            8800,
            9000,
            9200,
            9400,
            9600,
            9800,
            10000
          ]
        },
        "curve_every": 200,
        "final_app_err": 0.0312558983831845,
        "frac_any_violated": 0.5212,
        "include_box": true,
        "mean_pos": 0.007610177533091668,
        "structure": "frechet"
      }
    },
    {
      "mse": 0.010297478934410511,
      "n": 10000,
      "name": "bundle_diff(sample_steps=4,mc=16,median)",
      "static_arbitrage": {
        "M": 10,
        "curve": {
          "app_err": [
            0.00037341177463531497,
            0.00040967360138893127,
            0.00028969811896483106,
            0.00038977252319455147,
            0.00037108932435512545,
            0.00031779069453477857,
            0.0003465140398059573,
            0.0003031997848302126,
            0.00029374130070209504,
            0.0002733919247984886,
            0.00028166097334840083,
            0.00027331649791449307,
            0.0002679238597360941,
            0.00026446001471153326,
            0.0002548607972760995,
            0.00024179344880394637,
            0.0002588290469173123,
            0.00024634160618815156,
            0.00023337625849403833,
            0.00024284909758716822,
            0.0002348626839617888,
            0.00022442227483473041,
            0.00023126206725187923,
            0.00022917930114393434,
            0.00022295459285378457,
            0.00022471771718790898,
            0.00021901974178574704,
            0.00022440527100116016,
            0.00023397421464323997,
            0.00023091868621607622,
            0.00022841105117432534,
            0.0002258421160513535,
            0.00022060109415289128,
            0.00022581567494746517,
            0.00022493697011045048,
            0.0002217135624960065,
            0.00022233906478897947,
            0.00022383195053982108,
            0.0002213309289744267,
            0.00023547067586332559,
            0.0002355578478153159,
            0.00023891404714612734,
            0.0002497560903429985,
            0.0002507101956077597,
            0.00024845934328105715,
            0.0002487273441384668,
            0.0002469131643784807,
            0.00024674478297432266,
            0.0002457845332671185,
            0.0002524129182100296
          ],
          "t": [
            200,
            400,
            600,
            800,
            1000,
            1200,
            1400,
            1600,
            1800,
            2000,
            2200,
            2400,
            2600,
            2800,
            3000,
            3200,
            3400,
            3600,
            3800,
            4000,
            4200,
            4400,
            4600,
            4800,
            5000,
            5200,
            5400,
            5600,
            5800,
            6000,
            6200,
            6400,
            6600,
            6800,
            7000,
            7200,
            7400,
            7600,
            7800,
            8000,
            8200,
            8400,
            8600,
            8800,
            9000,
            9200,
            9400,
            9600,
            9800,
            10000
          ]
        },
        "curve_every": 200,
        "final_app_err": 0.0002524129182100296,
        "frac_any_violated": 0.0178,
        "include_box": true,
        "mean_pos": 2.6306972280144693e-05,
        "structure": "frechet"
      }
    },
    {
      "mse": 0.010477457321750495,
      "n": 10000,
      "name": "bundle_diff(sample_steps=8,mc=16,median)",
      "static_arbitrage": {
        "M": 10,
        "curve": {
          "app_err": [
            0.0001718945801258087,
            0.00016286492347717286,
            0.00011793430894613266,
            0.00024172884412109851,
            0.0002271111086010933,
            0.00020139153425892194,
            0.00018963005925927843,
            0.00016592630185186864,
            0.00017052753931946223,
            0.0001582600697875023,
            0.00016733292151581156,
            0.00017085771231601635,
            0.0001713179610669613,
            0.00016945789302034037,
            0.00016651276126503943,
            0.00016027514240704477,
            0.00016576492939801777,
            0.00015718521653778023,
            0.00014891231040421284,
            0.00015324373450130224,
            0.00014594641381076404,
            0.00014224670912054452,
            0.00013999715528410415,
            0.00014358554733917117,
            0.000139424280077219,
            0.00014072079283113662,
            0.00013728536734426464,
            0.00014216912311634848,
            0.00014735598181342256,
            0.00014490513938168685,
            0.000141892341235953,
            0.00014365357754286378,
            0.00014447224128878478,
            0.00014594999799395308,
            0.00014428849358643804,
            0.00014594221539381477,
            0.000144937685313257,
            0.00014507773136229892,
            0.00014820996242073865,
            0.0001535881827585399,
            0.00015547652388127838,
            0.00015493152884855156,
            0.00015823330773517144,
            0.0001608606796203689,
            0.00016188076469633315,
            0.00016553614612506784,
            0.00016273856638593877,
            0.00016369750800852975,
            0.0001625888467747338,
            0.00016736192628741264
          ],
          "t": [
            200,
            400,
            600,
            800,
            1000,
            1200,
            1400,
            1600,
            1800,
            2000,
            2200,
            2400,
            2600,
            2800,
            3000,
            3200,
            3400,
            3600,
            3800,
            4000,
            4200,
            4400,
            4600,
            4800,
            5000,
            5200,
            5400,
            5600,
            5800,
            6000,
            6200,
            6400,
            6600,
            6800,
            7000,
            7200,
            7400,
            7600,
            7800,
            8000,
            8200,
            8400,
            8600,
            8800,
            9000,
            9200,
            9400,
            9600,
            9800,
            10000
          ]
        },
        "curve_every": 200,
        "final_app_err": 0.00016736192628741264,
        "frac_any_violated": 0.0124,
        "include_box": true,
        "mean_pos": 1.6896492578089237e-05,
        "structure": "frechet"
      }
    },
    {
      "mse": 0.010668809912244285,
      "n": 10000,
      "name": "bundle_diff(sample_steps=16,mc=16,median)",
      "static_arbitrage": {
        "M": 10,
        "curve": {
          "app_err": [
            0.00018967822194099426,
            0.00018810994923114776,
            0.00012772238502899806,
            0.00028279385529458525,
            0.0002606305256485939,
            0.00024737187350789706,
            0.00021628998752151217,
            0.00018925373908132315,
            0.00019225982742177114,
            0.0001818414144217968,
            0.00019017652693119916,
            0.00019532343993584314,
            0.00019045374141289637,
            0.00018818266157593047,
            0.00018877873321374258,
            0.00018367834389209747,
            0.0001858969295726103,
            0.00017749230066935222,
            0.00016815060063412316,
            0.00016906782239675523,
            0.00016101697371119546,
            0.00015798550776459954,
            0.00015420266791530278,
            0.00015667165008683998,
            0.00015413158535957337,
            0.00015598281931418639,
            0.00015472370993208003,
            0.0001583880199385541,
            0.00016018764212213712,
            0.00015719969446460405,
            0.00015478532280652755,
            0.00015683072502724825,
            0.00015890702040809575,
            0.00016003621796913006,
            0.000157181409320661,
            0.0001599641242581937,
            0.0001579489594174398,
            0.00015661253495828103,
            0.00016000603874906515,
            0.00016468801605515183,
            0.00016682424809692835,
            0.00016649990098639613,
            0.00016884881808140943,
            0.00017012180062010883,
            0.00017129919905629424,
            0.0001734784551207786,
            0.0001700187726144461,
            0.00017090268918157865,
            0.00016860840138884224,
            0.00017211911119520664
          ],
          "t": [
            200,
            400,
            600,
            800,
            1000,
            1200,
            1400,
            1600,
            1800,
            2000,
            2200,
            2400,
            2600,
            2800,
            3000,
            3200,
            3400,
            3600,
            3800,
            4000,
            4200,
            4400,
            4600,
            4800,
            5000,
            5200,
            5400,
            5600,
            5800,
            6000,
            6200,
            6400,
            6600,
            6800,
            7000,
            7200,
            7400,
            7600,
            7800,
            8000,
            8200,
            8400,
            8600,
            8800,
            9000,
            9200,
            9400,
            9600,
            9800,
            10000
          ]
        },
        "curve_every": 200,
        "final_app_err": 0.00017211911119520664,
        "frac_any_violated": 0.0124,
        "include_box": true,
        "mean_pos": 1.735992718487978e-05,
        "structure": "frechet"
      }
    },
    {
      "mse": 0.01076893561179444,
      "n": 10000,
      "name": "bundle_diff(sample_steps=32,mc=16,median)",
      "static_arbitrage": {
        "M": 10,
        "curve": {
          "app_err": [
            0.000208624005317688,
            0.0002141810953617096,
            0.00014278739690780639,
            0.00031759724020957947,
            0.0002901008576154709,
            0.0002839121346672376,
            0.000249273878123079,
            0.00021811464335769415,
            0.00022327293538384967,
            0.00021507305093109607,
            0.0002229362777010961,
            0.00022815733371923366,
            0.00022100359058150877,
            0.0002173717732408217,
            0.00021844432627161344,
            0.00021327807218767702,
            0.00021739299792577238,
            0.00020745775041480858,
            0.00019653892144560814,
            0.00019711160752922298,
            0.00018772534050402187,
            0.00018430094911970875,
            0.0001787651597481707,
            0.00017982828198000788,
            0.00017850043550133706,
            0.0001806813170416997,
            0.00017966604136206485,
            0.00018226062413305045,
            0.00018197297728781044,
            0.00017805777800579867,
            0.00017522288726702813,
            0.00017732933221850544,
            0.00017980169448437113,
            0.00018109167706878746,
            0.0001776455720620496,
            0.0001816971470705337,
            0.00017956739694282816,
            0.00017773084195428772,
            0.00018176809765207462,
            0.00018660313007421792,
            0.00018922579838190137,
            0.00018845734962572654,
            0.00018960376226798047,
            0.00019100227414376356,
            0.00019127539441817336,
            0.0001927372325292748,
            0.00018924122775330188,
            0.00019004330950944375,
            0.00018732886210236015,
            0.00019155659172683954
          ],
          "t": [
            200,
            400,
            600,
            800,
            1000,
            1200,
            1400,
            1600,
            1800,
            2000,
            2200,
            2400,
            2600,
            2800,
            3000,
            3200,
            3400,
            3600,
            3800,
            4000,
            4200,
            4400,
            4600,
            4800,
            5000,
            5200,
            5400,
            5600,
            5800,
            6000,
            6200,
            6400,
            6600,
            6800,
            7000,
            7200,
            7400,
            7600,
            7800,
            8000,
            8200,
            8400,
            8600,
            8800,
            9000,
            9200,
            9400,
            9600,
            9800,
            10000
          ]
        },
        "curve_every": 200,
        "final_app_err": 0.00019155659172683954,
        "frac_any_violated": 0.012,
        "include_box": true,
        "mean_pos": 1.920131454244256e-05,
        "structure": "frechet"
      }
    },
    {
      "mse": 0.01082055179642201,
      "n": 10000,
      "name": "bundle_diff(sample_steps=64,mc=16,median)",
      "static_arbitrage": {
        "M": 10,
        "curve": {
          "app_err": [
            0.00021786779165267945,
            0.0002261801064014435,
            0.00015078673760096233,
            0.0003394268453121185,
            0.0003088614046573639,
            0.00030487500131130217,
            0.00026988948030131206,
            0.00023615329526364805,
            0.0002432634515894784,
            0.00023556210473179816,
            0.0002432161806659265,
            0.00024905172952761255,
            0.0002405705861747265,
            0.00023625806373144898,
            0.0002373541829486688,
            0.00023224786738865077,
            0.0002372961348908789,
            0.0002265002816501591,
            0.00021457921419488755,
            0.0002148546790704131,
            0.00020462350387658393,
            0.00020080947655845772,
            0.00019444877605723297,
            0.00019428468231732647,
            0.00019341510757803917,
            0.0001958455224163257,
            0.00019462950182733713,
            0.00019669499181743178,
            0.00019607825461646607,
            0.000191606717184186,
            0.00018864181433473864,
            0.00019080686790402977,
            0.0001936678673056039,
            0.00019522435579668072,
            0.00019150881309594426,
            0.00019631644969599115,
            0.00019405280063683922,
            0.00019219129542379004,
            0.00019624224935586637,
            0.00020118744112551212,
            0.0002040499975768531,
            0.00020305440007221132,
            0.00020332747940407243,
            0.00020472585985606366,
            0.00020441018376085492,
            0.00020574763174290242,
            0.00020221800008352766,
            0.0002030787686817348,
            0.00020003510449005633,
            0.0002047312293201685
          ],
          "t": [
            200,
            400,
            600,
            800,
            1000,
            1200,
            1400,
            1600,
            1800,
            2000,
            2200,
            2400,
            2600,
            2800,
            3000,
            3200,
            3400,
            3600,
            3800,
            4000,
            4200,
            4400,
            4600,
            4800,
            5000,
            5200,
            5400,
            5600,
            5800,
            6000,
            6200,
            6400,
            6600,
            6800,
            7000,
            7200,
            7400,
            7600,
            7800,
            8000,
            8200,
            8400,
            8600,
            8800,
            9000,
            9200,
            9400,
            9600,
            9800,
            10000
          ]
        },
        "curve_every": 200,
        "final_app_err": 0.0002047312293201685,
        "frac_any_violated": 0.013,
        "include_box": true,
        "mean_pos": 2.050849411636591e-05,
        "structure": "frechet"
      }
    }
  ],
  "train_meta": {
    "final_loss": 0.17559093326330186,
    "steps": 4000
  }
}
