{
  "results": [
    {
      "mse": 0.0,
      "n": 10000,
      "name": "oracle",
      "static_arbitrage": {
        "M": 10,
        "curve": {
          "app_err": [
            0.0,
            0.0,
            0.0,
            0.0,
            0.0,
            0.0,
            0.0,
            0.0,
            0.0,
            0.0,
            0.0,
            0.0,
            0.0,
            0.0,
            0.0,
            0.0,
            0.0,
            0.0,
            0.0,
            0.0,
            0.0,
            0.0,
            0.0,
            0.0,
            0.0,
            0.0,
            0.0,
            0.0,
            0.0,
            0.0,
            0.0,
            0.0,
            0.0,
            0.0,
            0.0,
            0.0,
            0.0,
            0.0,
            0.0,
            0.0,
            0.0,
            0.0,
            0.0,
            0.0,
            0.0,
            0.0,
            0.0,
            0.0,
            0.0,
            0.0
          ],
          "t": [
            200,
            400,
            600,
            800,
            1000,
            1200,
            1400,
            1600,
            1800,
            2000,
            2200,
            2400,
            2600,
            2800,
            3000,
            3200,
            3400,
            3600,
            3800,
            4000,
            4200,
            4400,
            4600,
            4800,
            5000,
            5200,
            5400,
            5600,
            5800,
            6000,
            6200,
            6400,
            6600,
            6800,
            7000,
            7200,
            7400,
            7600,
            7800,
            8000,
            8200,
            8400,
            8600,
            8800,
            9000,
            9200,
            9400,
            9600,
            9800,
            10000
          ]
        },
        "curve_every": 200,
        "final_app_err": 0.0,
        "frac_any_violated": 0.0,
        "include_box": true,
        "mean_pos": 0.0,
        "structure": "frechet"
      }
    },
    {
      "mse": 0.02022067555732445,
      "n": 10000,
      "name": "noisy(sigma=0.15)",
      "static_arbitrage": {
        "M": 10,
        "curve": {
          "app_err": [
            0.028203951997295335,
            0.026236695262940667,
            0.02650845503470971,
            0.02463803091247569,
            0.025512743756093043,
            0.024953820880097826,
            0.024950240624989517,
            0.025591848824193582,
            0.025892303066328805,
            0.027039421829982292,
            0.026307772909023693,
            0.026052416960970007,
            0.02652341944537036,
            0.026586794652147718,
            0.02703581763809517,
            0.026680077691017004,
            0.02703721178984765,
            0.027373471337812427,
            0.026957468731291248,
            0.026948947572189345,
            0.027069390737203027,
            0.026941051686762123,
            0.02712695006898852,
            0.027217829074517884,
            0.027523602805374553,
            0.027886985237226686,
            0.028092998969231543,
            0.028252104894931313,
            0.027922484599105672,
            0.028222350422743632,
            0.028233310177158782,
            0.028623859410021494,
            0.028541979005414234,
            0.028587701836446343,
            0.028640330774142228,
            0.028593029353077858,
            0.028435853189897258,
            0.028343892678837326,
            0.028215392370313182,
            0.028358360044764715,
            0.02840049380733498,
            0.028546948294098134,
            0.028465452661688144,
            0.028378476942675392,
            0.028491016322082955,
            0.028332039045755045,
            0.028344118607141103,
            0.028499691846732324,
            0.028523888784327153,
            0.02856283128165726
          ],
          "t": [
            200,
            400,
            600,
            800,
            1000,
            1200,
            1400,
            1600,
            1800,
            2000,
            2200,
            2400,
            2600,
            2800,
            3000,
            3200,
            3400,
            3600,
            3800,
            4000,
            4200,
            4400,
            4600,
            4800,
            5000,
            5200,
            5400,
            5600,
            5800,
            6000,
            6200,
            6400,
            6600,
            6800,
            7000,
            7200,
            7400,
            7600,
            7800,
            8000,
            8200,
            8400,
            8600,
            8800,
            9000,
            9200,
            9400,
            9600,
            9800,
            10000
          ]
        },
        "curve_every": 200,
        "final_app_err": 0.02856283128165726,
        "frac_any_violated": 0.5054,
        "include_box": true,
        "mean_pos": 0.007662454390704786,
        "structure": "frechet"
      }
    },
    {
      "mse": 0.0028365414167813648,
      "n": 10000,
      "name": "bundle_diff(sample_steps=4,mc=16,median)",
      "static_arbitrage": {
        "M": 10,
        "curve": {
          "app_err": [
            0.0001564134657382965,
            7.820673286914825e-05,
            5.21378219127655e-05,
            5.3922161459922794e-05,
            4.313772916793823e-05,
            5.8393751581509907e-05,
            7.314888494355338e-05,
            7.138233631849289e-05,
            7.818873557779524e-05,
            0.00011534637212753296,
            0.00011451253159479662,
            0.0001144593209028244,
            0.00010565475775645329,
            0.0001110223467860903,
            0.00010362085700035095,
            9.734698571264744e-05,
            9.36141873107237e-05,
            9.244898127184974e-05,
            9.946440003420178e-05,
            9.484575316309929e-05,
            9.84089236174311e-05,
            0.00010180700062350793,
            9.738060929205106e-05,
            0.00010067545808851719,
            9.66484397649765e-05,
            9.46228148845526e-05,
            9.190461701816983e-05,
            9.36910164143358e-05,
            9.461267754949372e-05,
            0.00010139029721419017,
            9.811964246534532e-05,
            9.826430585235357e-05,
            9.855353471004602e-05,
            9.988652213531383e-05,
            9.703262150287628e-05,
            9.692666120827199e-05,
            9.611959493643529e-05,
            9.359013191179226e-05,
            0.00010131257275740305,
            0.00010700598917901516,
            0.00010448505057067406,
            0.00010444337502121925,
            0.00010387319984824158,
            0.00010326926003802906,
            0.00010181855575905906,
            0.00010100295119311499,
            9.885395223155935e-05,
            9.995214253043135e-05,
            0.00010217712165749803,
            0.0001014503613114357
          ],
          "t": [
            200,
            400,
            600,
            800,
            1000,
            1200,
            1400,
            1600,
            1800,
            2000,
            2200,
            2400,
            2600,
            2800,
            3000,
            3200,
            3400,
            3600,
            3800,
            4000,
            4200,
            4400,
            4600,
            4800,
            5000,
            5200,
            5400,
            5600,
            5800,
            6000,
            6200,
            6400,
            6600,
            6800,
            7000,
            7200,
            7400,
            7600,
            7800,
            8000,
            8200,
            8400,
            8600,
            8800,
            9000,
            9200,
            9400,
            9600,
            9800,
            10000
          ]
        },
        "curve_every": 200,
        "final_app_err": 0.0001014503613114357,
        "frac_any_violated": 0.0142,
        "include_box": true,
        "mean_pos": 1.3288744837045669e-05,
        "structure": "frechet"
      }
    },
    {
      "mse": 0.0028424327294080455,
      "n": 10000,
      "name": "bundle_diff(sample_steps=8,mc=16,median)",
      "static_arbitrage": {
        "M": 10,
        "curve": {
          "app_err": [
            6.328925490379334e-05,
            3.164462745189667e-05,
            2.1096418301264445e-05,
            1.5822313725948335e-05,
            1.9691437482833863e-05,
            2.6680702964464825e-05,
            2.5925615004130772e-05,
            2.935348078608513e-05,
            3.537825412220425e-05,
            4.613909125328064e-05,
            4.989556290886619e-05,
            4.573759933312734e-05,
            4.221932246134832e-05,
            5.085773766040802e-05,
            4.746722181638082e-05,
            4.9631381407380105e-05,
            4.725283559630899e-05,
            4.5108323295911156e-05,
            4.6544192652953296e-05,
            4.421698302030564e-05,
            4.930233671551659e-05,
            5.084469237110832e-05,
            4.8634053572364476e-05,
            5.061281844973564e-05,
            4.858830571174622e-05,
            4.875756227053129e-05,
            4.695172663088198e-05,
            4.5333579182624815e-05,
            4.4008293028535514e-05,
            4.396714270114899e-05,
            4.3383524302513366e-05,
            4.423021338880062e-05,
            4.445659843358126e-05,
            4.3863662902046654e-05,
            4.26104153905596e-05,
            4.367763900922404e-05,
            4.249716227924502e-05,
            4.1503805275026124e-05,
            4.278667175616973e-05,
            4.736414272338152e-05,
            4.620891973012831e-05,
            4.510870735560145e-05,
            4.5485279068004256e-05,
            4.445152272554961e-05,
            4.359560956557592e-05,
            4.264787892284601e-05,
            4.174047724363652e-05,
            4.2418341618031267e-05,
            4.585895079131029e-05,
            4.576909616589546e-05
          ],
          "t": [
            200,
            400,
            600,
            800,
            1000,
            1200,
            1400,
            1600,
            1800,
            2000,
            2200,
            2400,
            2600,
            2800,
            3000,
            3200,
            3400,
            3600,
            3800,
            4000,
            4200,
            4400,
            4600,
            4800,
            5000,
            5200,
            5400,
            5600,
            5800,
            6000,
            6200,
            6400,
            6600,
            6800,
            7000,
            7200,
            7400,
            7600,
            7800,
            8000,
            8200,
            8400,
            8600,
            8800,
            9000,
            9200,
            9400,
            9600,
            9800,
            10000
          ]
        },
        "curve_every": 200,
        "final_app_err": 4.576909616589546e-05,
        "frac_any_violated": 0.0069,
        "include_box": true,
        "mean_pos": 5.15825591981411e-06,
        "structure": "frechet"
      }
    },
    {
      "mse": 0.0029002600224189066,
      "n": 10000,
      "name": "bundle_diff(sample_steps=16,mc=16,median)",
      "static_arbitrage": {
        "M": 10,
        "curve": {
          "app_err": [
            5.552694201469421e-05,
            2.7763471007347106e-05,
            1.8508980671564736e-05,
            1.3881735503673553e-05,
            2.385607361793518e-05,
            2.8099417686462403e-05,
            2.908991915839059e-05,
            3.8781706243753434e-05,
            4.630325569046868e-05,
            5.672707408666611e-05,
            6.601499562913721e-05,
            6.051374599337578e-05,
            5.766746516411121e-05,
            6.378051957913807e-05,
            5.952848494052887e-05,
            6.076018791645765e-05,
            5.849569597665001e-05,
            5.570388088623683e-05,
            5.630327290610263e-05,
            5.34881092607975e-05,
            5.8565036881537665e-05,
            5.882178179242394e-05,
            5.6264313018840295e-05,
            5.7299834055205185e-05,
            5.5511333048343655e-05,
            5.936667179832092e-05,
            5.7167906176160886e-05,
            5.648455316466945e-05,
            5.453680995209464e-05,
            5.597282573580742e-05,
            5.456456854458778e-05,
            5.6157048093155026e-05,
            5.605075959906433e-05,
            5.467845784390674e-05,
            5.311621619122369e-05,
            5.39802232136329e-05,
            5.39454143192317e-05,
            5.395720369721714e-05,
            5.420485845743082e-05,
            5.740045104175806e-05,
            5.643121443870591e-05,
            5.5087614094927195e-05,
            5.6374666475972466e-05,
            5.5093424056064e-05,
            5.416293690601985e-05,
            5.298876649011736e-05,
            5.1861345926497845e-05,
            5.342674829686681e-05,
            5.7630591398599196e-05,
            5.647797957062721e-05
          ],
          "t": [
            200,
            400,
            600,
            800,
            1000,
            1200,
            1400,
            1600,
            1800,
            2000,
            2200,
            2400,
            2600,
            2800,
            3000,
            3200,
            3400,
            3600,
            3800,
            4000,
            4200,
            4400,
            4600,
            4800,
            5000,
            5200,
            5400,
            5600,
            5800,
            6000,
            6200,
            6400,
            6600,
            6800,
            7000,
            7200,
            7400,
            7600,
            7800,
            8000,
            8200,
            8400,
            8600,
            8800,
            9000,
            9200,
            9400,
            9600,
            9800,
            10000
          ]
        },
        "curve_every": 200,
        "final_app_err": 5.647797957062721e-05,
        "frac_any_violated": 0.0077,
        "include_box": true,
        "mean_pos": 5.924633368849754e-06,
        "structure": "frechet"
      }
    },
    {
      "mse": 0.002936027069988866,
      "n": 10000,
      "name": "bundle_diff(sample_steps=32,mc=16,median)",
      "static_arbitrage": {
        "M": 10,
        "curve": {
          "app_err": [
            5.609065294265747e-05,
            2.8045326471328734e-05,
            1.8696884314219157e-05,
            1.4022663235664367e-05,
            1.9334912300109865e-05,
            1.92644198735555e-05,
            2.1247374159949167e-05,
            2.5867111980915068e-05,
            3.339721096886529e-05,
            4.027930647134781e-05,
            5.166332152756778e-05,
            4.7358044733603794e-05,
            4.371511821563427e-05,
            5.0136867378439224e-05,
            4.679440955320994e-05,
            4.745237063616514e-05,
            4.575673709897434e-05,
            4.321469614903132e-05,
            4.378465053282286e-05,
            4.1595418006181715e-05,
            4.686435241074789e-05,
            4.473415457389571e-05,
            4.278919133155242e-05,
            4.439409822225571e-05,
            4.3122148513793946e-05,
            4.780710603182132e-05,
            4.60364724750872e-05,
            4.466643024768148e-05,
            4.312620851500281e-05,
            4.5244050522645315e-05,
            4.378456502191482e-05,
            4.5939739793539046e-05,
            4.584884779019789e-05,
            4.450035226695678e-05,
            4.322891363075801e-05,
            4.42418973479006e-05,
            4.547516437801155e-05,
            4.614403569384625e-05,
            4.592887675150847e-05,
            4.8263376578688624e-05,
            4.7476238957265526e-05,
            4.690320984948249e-05,
            4.818172908799593e-05,
            4.7086689790541475e-05,
            4.6462280054887135e-05,
            4.545223048847655e-05,
            4.4485161754679175e-05,
            4.6210191988696655e-05,
            5.002258307471567e-05,
            4.902213141322136e-05
          ],
          "t": [
            200,
            400,
            600,
            800,
            1000,
            1200,
            1400,
            1600,
            1800,
            2000,
            2200,
            2400,
            2600,
            2800,
            3000,
            3200,
            3400,
            3600,
            3800,
            4000,
            4200,
            4400,
            4600,
            4800,
            5000,
            5200,
            5400,
            5600,
            5800,
            6000,
            6200,
            6400,
            6600,
            6800,
            7000,
            7200,
            7400,
            7600,
            7800,
            8000,
            8200,
            8400,
            8600,
            8800,
            9000,
            9200,
            9400,
            9600,
            9800,
            10000
          ]
        },
        "curve_every": 200,
        "final_app_err": 4.902213141322136e-05,
        "frac_any_violated": 0.0065,
        "include_box": true,
        "mean_pos": 5.059146359562874e-06,
        "structure": "frechet"
      }
    },
    {
      "mse": 0.002958011846844224,
      "n": 10000,
      "name": "bundle_diff(sample_steps=64,mc=16,median)",
      "static_arbitrage": {
        "M": 10,
        "curve": {
          "app_err": [
            6.749868392944336e-05,
            3.374934196472168e-05,
            2.2499561309814454e-05,
            1.687467098236084e-05,
            1.9414544105529784e-05,
            1.8084098895390827e-05,
            2.069371087210519e-05,
            2.3517459630966187e-05,
            3.1032247675789725e-05,
            3.649812936782837e-05,
            4.925391890785911e-05,
            4.514942566553752e-05,
            4.167639292203463e-05,
            4.8734758581433974e-05,
            4.548577467600505e-05,
            4.562107846140862e-05,
            4.440472406499526e-05,
            4.199056161774529e-05,
            4.2891745504580045e-05,
            4.0747158229351044e-05,
            4.700103331179846e-05,
            4.486462270671671e-05,
            4.291398693685946e-05,
            4.4620264476786056e-05,
            4.3436626344919204e-05,
            4.831648145157557e-05,
            4.6526982138554256e-05,
            4.486530420503446e-05,
            4.3318224749688445e-05,
            4.557938314974308e-05,
            4.4109080467493306e-05,
            4.638521175365895e-05,
            4.659561214573456e-05,
            4.5225152964977654e-05,
            4.398357602102416e-05,
            4.5262587049769034e-05,
            4.7204884624964485e-05,
            4.843672982564098e-05,
            4.800161633353967e-05,
            5.065542971715331e-05,
            4.975884925664925e-05,
            4.95153714326166e-05,
            5.080781833723534e-05,
            4.965309519320727e-05,
            4.91609453327126e-05,
            4.809222912982754e-05,
            4.7068990212171635e-05,
            4.89072249426196e-05,
            5.2799106176410404e-05,
            5.174312405288219e-05
          ],
          "t": [
            200,
            400,
            600,
            800,
            1000,
            1200,
            1400,
            1600,
            1800,
            2000,
            2200,
            2400,
            2600,
            2800,
            3000,
            3200,
            3400,
            3600,
            3800,
            4000,
            4200,
            4400,
            4600,
            4800,
            5000,
            5200,
            5400,
            5600,
            5800,
            6000,
            6200,
            6400,
            6600,
            6800,
            7000,
            7200,
            7400,
            7600,
            7800,
            8000,
            8200,
            8400,
            8600,
            8800,
            9000,
            9200,
            9400,
            9600,
            9800,
            10000
          ]
        },
        "curve_every": 200,
        "final_app_err": 5.174312405288219e-05,
        "frac_any_violated": 0.007,
        "include_box": true,
        "mean_pos": 5.349840633571148e-06,
        "structure": "frechet"
      }
    }
  ],
  "train_meta": {
    "final_loss": 0.10913690660148859,
    "steps": 4000
  }
}
